setup.py
journaler/__init__.py
journaler/log.py
journaler/models.py
journaler/validate.py
journaler.egg-info/PKG-INFO
journaler.egg-info/SOURCES.txt
journaler.egg-info/dependency_links.txt
journaler.egg-info/entry_points.txt
journaler.egg-info/requires.txt
journaler.egg-info/top_level.txt