Metadata-Version: 1.1
Name: journaler
Version: 1.2
Summary: Tool to support logging of diet and mood
Home-page: https://github.com/Bachmann1234/journaler
Author: Matt Bachmann
Author-email: bachmann.matt@gmail.com
License: Apache 2.0
Platform: UNKNOWN
Classifier: Development Status :: 5 - Production/Stable
Classifier: Environment :: Console
Classifier: License :: OSI Approved :: Apache Software License
Classifier: Operating System :: OS Independent
Classifier: Programming Language :: Python
